MANIFEST.in
setup.py
conf/gps.conf
rtlsdr_scanner/__init__.py
rtlsdr_scanner/__main__.py
rtlsdr_scanner/cli.py
rtlsdr_scanner/constants.py
rtlsdr_scanner/devices.py
rtlsdr_scanner/dialogs_devices.py
rtlsdr_scanner/dialogs_file.py
rtlsdr_scanner/dialogs_help.py
rtlsdr_scanner/dialogs_prefs.py
rtlsdr_scanner/dialogs_scan.py
rtlsdr_scanner/dialogs_toolbars.py
rtlsdr_scanner/dialogs_tools.py
rtlsdr_scanner/events.py
rtlsdr_scanner/file.py
rtlsdr_scanner/location.py
rtlsdr_scanner/main_window.py
rtlsdr_scanner/menus.py
rtlsdr_scanner/misc.py
rtlsdr_scanner/panels.py
rtlsdr_scanner/plot_3d.py
rtlsdr_scanner/plot_controls.py
rtlsdr_scanner/plot_line.py
rtlsdr_scanner/plot_preview.py
rtlsdr_scanner/plot_spect.py
rtlsdr_scanner/plot_status.py
rtlsdr_scanner/plot_time.py
rtlsdr_scanner/printer.py
rtlsdr_scanner/rtlsdr_scan_diag.py
rtlsdr_scanner/rtlsdr_scan_view.py
rtlsdr_scanner/rtltcp.py
rtlsdr_scanner/scan.py
rtlsdr_scanner/settings.py
rtlsdr_scanner/spectrum.py
rtlsdr_scanner/toolbars.py
rtlsdr_scanner/utils_google.py
rtlsdr_scanner/utils_mpl.py
rtlsdr_scanner/utils_wx.py
rtlsdr_scanner/version.py
rtlsdr_scanner/widgets.py
rtlsdr_scanner.egg-info/PKG-INFO
rtlsdr_scanner.egg-info/SOURCES.txt
rtlsdr_scanner.egg-info/dependency_links.txt
rtlsdr_scanner.egg-info/requires.txt
rtlsdr_scanner.egg-info/top_level.txt
rtlsdr_scanner/res/__init__.py
rtlsdr_scanner/res/__init__.pyc
rtlsdr_scanner/res/auto_f.png
rtlsdr_scanner/res/auto_l.png
rtlsdr_scanner/res/auto_refresh.png
rtlsdr_scanner/res/auto_t.png
rtlsdr_scanner/res/average.png
rtlsdr_scanner/res/busy.gif
rtlsdr_scanner/res/colourmap.png
rtlsdr_scanner/res/crosshair.png
rtlsdr_scanner/res/delta.png
rtlsdr_scanner/res/diff.png
rtlsdr_scanner/res/fade.png
rtlsdr_scanner/res/get_gjson.js
rtlsdr_scanner/res/gmaps.js
rtlsdr_scanner/res/grid.png
rtlsdr_scanner/res/icon.png
rtlsdr_scanner/res/max.png
rtlsdr_scanner/res/min.png
rtlsdr_scanner/res/peak.png
rtlsdr_scanner/res/peaks.png
rtlsdr_scanner/res/rtlsdr_scan.html
rtlsdr_scanner/res/smooth.png
rtlsdr_scanner/res/spacer.png
rtlsdr_scanner/res/variance.png
rtlsdr_scanner/res/wireframe.png